<?xml version="1.0" encoding="UTF-8"?><record_update table="sp_js_include">
    <sp_js_include action="INSERT_OR_UPDATE">
        <display_name>dark theme</display_name>
        <source>local</source>
        <sys_class_name>sp_js_include</sys_class_name>
        <sys_created_by>bareen.makhdoomi</sys_created_by>
        <sys_created_on>2026-03-02 10:05:42</sys_created_on>
        <sys_id>40e783faebd77210084cfd50dad0cd80</sys_id>
        <sys_mod_count>0</sys_mod_count>
        <sys_name>dark theme</sys_name>
        <sys_package display_value="Data Migration" source="x_sysus_data_mig_0">9977a0f8eb03f610084cfd50dad0cd43</sys_package>
        <sys_policy/>
        <sys_scope display_value="Data Migration">9977a0f8eb03f610084cfd50dad0cd43</sys_scope>
        <sys_ui_script display_value="x_sysus_data_mig_0.dark theme">cff747faebd77210084cfd50dad0cd0a</sys_ui_script>
        <sys_update_name>sp_js_include_40e783faebd77210084cfd50dad0cd80</sys_update_name>
        <sys_updated_by>bareen.makhdoomi</sys_updated_by>
        <sys_updated_on>2026-03-02 10:05:42</sys_updated_on>
        <url/>
    </sp_js_include>
</record_update>
